osparc_filecomms/__init__.py
osparc_filecomms/_version.py
osparc_filecomms/handshakers.py
osparc_filecomms/tools.py
osparc_filecomms-1.0.6.dist-info/LICENSE.txt
osparc_filecomms-1.0.6.dist-info/METADATA
osparc_filecomms-1.0.6.dist-info/WHEEL
osparc_filecomms-1.0.6.dist-info/top_level.txt
osparc_filecomms-1.0.6.dist-info/RECORD
