Metadata-Version: 2.1
Name: osparc_filecomms
Version: 1.0.6
Summary: oSparc file communications
Author: Werner Van Geit @ IT'IS Zurich
License: Copyright (C) IT'IS Foundation - All Rights Reserved
License-File: LICENSE.txt
Requires-Dist: watchdog
Provides-Extra: test
Requires-Dist: pytest; extra == "test"
Requires-Dist: pytest-mock; extra == "test"
